ddf/__init__.py
django_dynamic_fixture/__init__.py
django_dynamic_fixture/ddf.py
django_dynamic_fixture/decorators.py
django_dynamic_fixture/django_helper.py
django_dynamic_fixture/fdf.py
django_dynamic_fixture/fields.py
django_dynamic_fixture/global_settings.py
django_dynamic_fixture/models.py
django_dynamic_fixture/models_sample_app.py
django_dynamic_fixture/models_test.py
django_dynamic_fixture/models_third_party.py
django_dynamic_fixture/script_ddf_checkings.py
django_dynamic_fixture/fixture_algorithms/__init__.py
django_dynamic_fixture/fixture_algorithms/default_fixture.py
django_dynamic_fixture/fixture_algorithms/random_fixture.py
django_dynamic_fixture/fixture_algorithms/sequential_fixture.py
django_dynamic_fixture/fixture_algorithms/unique_random_fixture.py
django_dynamic_fixture/fixture_algorithms/tests/__init__.py
django_dynamic_fixture/fixture_algorithms/tests/abstract_test_generic_fixture.py
django_dynamic_fixture/fixture_algorithms/tests/test_default_fixture.py
django_dynamic_fixture/fixture_algorithms/tests/test_default_fixture_postgres.py
django_dynamic_fixture/fixture_algorithms/tests/test_random_fixture.py
django_dynamic_fixture/fixture_algorithms/tests/test_sequential_fixture.py
django_dynamic_fixture/fixture_algorithms/tests/test_unique_random_fixture.py
django_dynamic_fixture/tests/__init__.py
django_dynamic_fixture/tests/conftest.py
django_dynamic_fixture/tests/test_ddf.py
django_dynamic_fixture/tests/test_ddf_checkings.py
django_dynamic_fixture/tests/test_ddf_copier.py
django_dynamic_fixture/tests/test_ddf_custom_fields.py
django_dynamic_fixture/tests/test_ddf_custom_models.py
django_dynamic_fixture/tests/test_ddf_geo.py
django_dynamic_fixture/tests/test_ddf_signals.py
django_dynamic_fixture/tests/test_ddf_teaching_and_lessons.py
django_dynamic_fixture/tests/test_decorators.py
django_dynamic_fixture/tests/test_django_helper.py
django_dynamic_fixture/tests/test_fdf.py
django_dynamic_fixture/tests/test_global_settings.py
django_dynamic_fixture-4.0.1.dist-info/LICENSE.txt
django_dynamic_fixture-4.0.1.dist-info/METADATA
django_dynamic_fixture-4.0.1.dist-info/WHEEL
django_dynamic_fixture-4.0.1.dist-info/top_level.txt
django_dynamic_fixture-4.0.1.dist-info/RECORD
