Metadata-Version: 2.1
Name: django-dynamic-fixture
Version: 4.0.1
Summary: A full library to create dynamic model instances for testing purposes.
Home-page: https://github.com/paulocheque/django-dynamic-fixture
Author: paulocheque
Author-email: paulocheque@gmail.com
License: MIT
Keywords: python django testing fixture
Classifier: Framework :: Django
Classifier: Operating System :: OS Independent
Classifier: Topic :: Software Development
Classifier: Programming Language :: Python :: 3.8
Classifier: Programming Language :: Python :: 3.9
Classifier: Programming Language :: Python :: 3.10
Classifier: Programming Language :: Python :: 3.11
Classifier: Programming Language :: Python :: Implementation :: PyPy
License-File: LICENSE.txt
Provides-Extra: test
